README.md
plotbox/__init__.py
plotbox/iplot.py
plotbox/movie.py
plotbox/plot.py
plotbox/version.py
plotbox/utils/__init__.py
plotbox/utils/date.py
plotbox-0.1.0.dist-info/DESCRIPTION.rst
plotbox-0.1.0.dist-info/METADATA
plotbox-0.1.0.dist-info/RECORD
plotbox-0.1.0.dist-info/WHEEL
plotbox-0.1.0.dist-info/metadata.json
plotbox-0.1.0.dist-info/pbr.json
plotbox-0.1.0.dist-info/top_level.txt
tests/__init__.py
tests/plot_tests.py
