Metadata-Version: 2.0
Name: plotbox
Version: 0.1.0
Summary: Plotting library with a common API for static and interactive visualization
Home-page: https://github.com/anmolgarg/plotbox
Author: Anmol Garg
Author-email: anmolgarg314@gmail.com
License: MIT
Keywords: plotting visualization interactive
Platform: UNKNOWN
Classifier: Development Status :: 2 - Pre-Alpha
Classifier: Topic :: Scientific/Engineering :: Visualization
Requires-Dist: matplotlib
Requires-Dist: numpy
Requires-Dist: pandas
Requires-Dist: plotly
Requires-Dist: seaborn
